a2anet/__about__.py
a2anet/__init__.py
a2anet/executors/__init__.py
a2anet/executors/langgraph.py
a2anet/types/__init__.py
a2anet/types/langgraph.py
a2anet-0.2.0.dist-info/METADATA
a2anet-0.2.0.dist-info/WHEEL
a2anet-0.2.0.dist-info/licenses/LICENSE
a2anet-0.2.0.dist-info/RECORD
