Metadata-Version: 2.4
Name: a2anet
Version: 0.2.0
Summary: A package that makes implementing the A2A protocol easy
Project-URL: Documentation, https://github.com/A2ANet/A2ANetPython#readme
Project-URL: Issues, https://github.com/A2ANet/A2ANetPython/issues
Project-URL: Source, https://github.com/A2ANet/A2ANetPython
Author-email: A2A Net <hello@a2anet.com>
License-Expression: Apache-2.0
License-File: LICENSE
Classifier: Development Status :: 4 - Beta
Classifier: Programming Language :: Python
Classifier: Programming Language :: Python :: 3.13
Classifier: Programming Language :: Python :: Implementation :: CPython
Classifier: Programming Language :: Python :: Implementation :: PyPy
Requires-Python: >=3.13
Requires-Dist: a2a-sdk==0.3.0
Requires-Dist: langgraph
Requires-Dist: loguru
Requires-Dist: pydantic
